analog_hub/__init__.py
analog_hub/cli/__init__.py
analog_hub/cli/main.py
analog_hub/cli/commands/__init__.py
analog_hub/core/__init__.py
analog_hub/core/config.py
analog_hub/utils/__init__.py
analog_hub-0.0.0.dist-info/METADATA
analog_hub-0.0.0.dist-info/WHEEL
analog_hub-0.0.0.dist-info/entry_points.txt
analog_hub-0.0.0.dist-info/top_level.txt
analog_hub-0.0.0.dist-info/RECORD
